<?xml version="1.0" encoding="utf-8"?>
<SettingsBlock>
	<ModSettings Class="SRTS.SRTS_ModSettings">
		<defProperties>
			<keys>
				<li>SRTSSuperpod</li>
				<li>SRTSSkip</li>
				<li>SRAF</li>
				<li>SRAFTek</li>
				<li>SRTSMkII</li>
				<li>SRTSMkIII</li>
				<li>SRTSMkIIIp</li>
				<li>SRTSMkIV</li>
				<li>Bf110C7a</li>
				<li>HE111a</li>
				<li>LKPV1C7a</li>
				<li>Lp38la</li>
				<li>AvroYork685a</li>
				<li>JU52a</li>
				<li>MFF50a</li>
				<li>NAP51Da</li>
				<li>tu2da</li>
				<li>YAK9Ba</li>
				<li>A6M7a</li>
				<li>B29SFa</li>
				<li>ME262a</li>
				<li>JU87stua</li>
				<li>AvroLana</li>
				<li>AR234Ba</li>
				<li>DC133a</li>
				<li>DCA3a</li>
				<li>MM4a</li>
				<li>MIG19a</li>
				<li>F100a</li>
				<li>BR1001a</li>
				<li>AVROVULCANa</li>
				<li>AEROL29a</li>
				<li>MIRAGEIIIa</li>
				<li>F111Ka</li>
				<li>SU15a</li>
				<li>he177a</li>
				<li>B52a</li>
				<li>C130a</li>
				<li>DO217a</li>
				<li>TU95a</li>
				<li>mig29a</li>
				<li>F16a</li>
				<li>mig27a</li>
				<li>PNTa</li>
				<li>A10a</li>
				<li>ME1075a</li>
				<li>fa18a</li>
				<li>HAIIa</li>
				<li>AN225a</li>
				<li>F16XLa</li>
				<li>yak41a</li>
				<li>MIG144a</li>
				<li>SU47a</li>
				<li>B2a</li>
				<li>X44a</li>
				<li>V22OSa</li>
				<li>JH7a</li>
				<li>F4IIa</li>
				<li>C17GBa</li>
				<li>C5Ga</li>
				<li>B1La</li>
				<li>F117a</li>
				<li>XB35a</li>
				<li>J10a</li>
				<li>J20a</li>
				<li>JCC16a</li>
				<li>FA223a</li>
				<li>PHRP</li>
				<li>SKR4a</li>
				<li>MI4a</li>
				<li>UH1a</li>
				<li>MI12a</li>
				<li>mi8a</li>
				<li>CH53a</li>
				<li>AH56C</li>
				<li>MI24A</li>
				<li>AH1C</li>
			</keys>
			<values>
				<li>
					<defaultValues>True</defaultValues>
					<massCapacity>120</massCapacity>
					<minPassengers>1</minPassengers>
					<maxPassengers>1</maxPassengers>
					<flightSpeed>1</flightSpeed>
					<researchPoints>4800</researchPoints>
					<fuelPerTile>3.5</fuelPerTile>
					<customResearchDefNames />
					<radiusDrop>1</radiusDrop>
					<distanceBetweenDrops>10</distanceBetweenDrops>
					<bombingSpeed>1</bombingSpeed>
					<precisionBombingNumBombs>1</precisionBombingNumBombs>
				</li>
				<li>
					<defaultValues>True</defaultValues>
					<massCapacity>170</massCapacity>
					<minPassengers>1</minPassengers>
					<maxPassengers>2</maxPassengers>
					<flightSpeed>3</flightSpeed>
					<researchPoints>6200</researchPoints>
					<fuelPerTile>2.25</fuelPerTile>
					<shuttleBayLanding>True</shuttleBayLanding>
					<customResearchDefNames />
					<bombingCapable>True</bombingCapable>
					<numberBombs>4</numberBombs>
					<radiusDrop>3</radiusDrop>
					<distanceBetweenDrops>3</distanceBetweenDrops>
					<bombingSpeed>1</bombingSpeed>
					<precisionBombingNumBombs>4</precisionBombingNumBombs>
				</li>
				<li>
					<defaultValues>True</defaultValues>
					<massCapacity>5000</massCapacity>
					<minPassengers>1</minPassengers>
					<maxPassengers>3</maxPassengers>
					<flightSpeed>3</flightSpeed>
					<researchPoints>7200</researchPoints>
					<fuelPerTile>4</fuelPerTile>
					<customResearchDefNames />
					<radiusDrop>1</radiusDrop>
					<distanceBetweenDrops>10</distanceBetweenDrops>
					<bombingSpeed>1</bombingSpeed>
					<precisionBombingNumBombs>1</precisionBombingNumBombs>
				</li>
				<li>
					<defaultValues>True</defaultValues>
					<massCapacity>10000</massCapacity>
					<minPassengers>1</minPassengers>
					<maxPassengers>28</maxPassengers>
					<flightSpeed>8</flightSpeed>
					<researchPoints>12000</researchPoints>
					<fuelPerTile>2.25</fuelPerTile>
					<spaceFaring>True</spaceFaring>
					<customResearchDefNames />
					<radiusDrop>1</radiusDrop>
					<distanceBetweenDrops>10</distanceBetweenDrops>
					<bombingSpeed>1</bombingSpeed>
					<precisionBombingNumBombs>1</precisionBombingNumBombs>
				</li>
				<li>
					<defaultValues>True</defaultValues>
					<massCapacity>2200</massCapacity>
					<minPassengers>1</minPassengers>
					<maxPassengers>7</maxPassengers>
					<flightSpeed>11</flightSpeed>
					<researchPoints>12000</researchPoints>
					<fuelPerTile>2</fuelPerTile>
					<spaceFaring>True</spaceFaring>
					<shuttleBayLanding>True</shuttleBayLanding>
					<customResearchDefNames />
					<bombingCapable>True</bombingCapable>
					<numberBombs>6</numberBombs>
					<radiusDrop>4</radiusDrop>
					<distanceBetweenDrops>3</distanceBetweenDrops>
					<bombingSpeed>1</bombingSpeed>
					<precisionBombingNumBombs>20</precisionBombingNumBombs>
				</li>
				<li>
					<defaultValues>True</defaultValues>
					<massCapacity>3600</massCapacity>
					<minPassengers>1</minPassengers>
					<maxPassengers>17</maxPassengers>
					<flightSpeed>20</flightSpeed>
					<researchPoints>24000</researchPoints>
					<fuelPerTile>1</fuelPerTile>
					<spaceFaring>True</spaceFaring>
					<shuttleBayLanding>True</shuttleBayLanding>
					<customResearchDefNames />
					<bombingCapable>True</bombingCapable>
					<numberBombs>20</numberBombs>
					<radiusDrop>5</radiusDrop>
					<distanceBetweenDrops>2</distanceBetweenDrops>
					<bombingSpeed>1</bombingSpeed>
					<precisionBombingNumBombs>10</precisionBombingNumBombs>
				</li>
				<li>
					<defaultValues>True</defaultValues>
					<massCapacity>20000</massCapacity>
					<minPassengers>1</minPassengers>
					<maxPassengers>42</maxPassengers>
					<flightSpeed>20</flightSpeed>
					<researchPoints>20000</researchPoints>
					<fuelPerTile>1</fuelPerTile>
					<spaceFaring>True</spaceFaring>
					<customResearchDefNames />
					<radiusDrop>1</radiusDrop>
					<distanceBetweenDrops>10</distanceBetweenDrops>
					<bombingSpeed>1</bombingSpeed>
					<precisionBombingNumBombs>1</precisionBombingNumBombs>
				</li>
				<li>
					<defaultValues>True</defaultValues>
					<massCapacity>1E+09</massCapacity>
					<minPassengers>1</minPassengers>
					<maxPassengers>9999</maxPassengers>
					<flightSpeed>80</flightSpeed>
					<researchPoints>36000</researchPoints>
					<fuelPerTile>1</fuelPerTile>
					<spaceFaring>True</spaceFaring>
					<customResearchDefNames />
					<bombingCapable>True</bombingCapable>
					<numberBombs>32</numberBombs>
					<radiusDrop>9</radiusDrop>
					<distanceBetweenDrops>1</distanceBetweenDrops>
					<bombingSpeed>0.7</bombingSpeed>
					<precisionBombingNumBombs>32</precisionBombingNumBombs>
				</li>
				<li>
					<defaultValues>True</defaultValues>
					<massCapacity>500</massCapacity>
					<minPassengers>1</minPassengers>
					<maxPassengers>2</maxPassengers>
					<flightSpeed>8</flightSpeed>
					<researchPoints>850</researchPoints>
					<fuelPerTile>7.75</fuelPerTile>
					<customResearchDefNames />
					<bombingCapable>True</bombingCapable>
					<numberBombs>2</numberBombs>
					<radiusDrop>4</radiusDrop>
					<distanceBetweenDrops>3</distanceBetweenDrops>
					<bombingSpeed>0.8</bombingSpeed>
					<precisionBombingNumBombs>2</precisionBombingNumBombs>
				</li>
				<li>
					<defaultValues>True</defaultValues>
					<massCapacity>1500</massCapacity>
					<minPassengers>2</minPassengers>
					<maxPassengers>4</maxPassengers>
					<flightSpeed>7</flightSpeed>
					<researchPoints>850</researchPoints>
					<fuelPerTile>7.75</fuelPerTile>
					<customResearchDefNames />
					<bombingCapable>True</bombingCapable>
					<numberBombs>6</numberBombs>
					<radiusDrop>4</radiusDrop>
					<distanceBetweenDrops>4</distanceBetweenDrops>
					<bombingSpeed>0.7</bombingSpeed>
					<precisionBombingNumBombs>6</precisionBombingNumBombs>
				</li>
				<li>
					<defaultValues>True</defaultValues>
					<massCapacity>600</massCapacity>
					<minPassengers>2</minPassengers>
					<maxPassengers>4</maxPassengers>
					<flightSpeed>7</flightSpeed>
					<researchPoints>850</researchPoints>
					<fuelPerTile>8.75</fuelPerTile>
					<customResearchDefNames />
					<bombingCapable>True</bombingCapable>
					<numberBombs>6</numberBombs>
					<radiusDrop>6</radiusDrop>
					<distanceBetweenDrops>3</distanceBetweenDrops>
					<bombingSpeed>0.8</bombingSpeed>
					<precisionBombingNumBombs>6</precisionBombingNumBombs>
				</li>
				<li>
					<defaultValues>True</defaultValues>
					<massCapacity>390</massCapacity>
					<minPassengers>1</minPassengers>
					<maxPassengers>1</maxPassengers>
					<flightSpeed>8</flightSpeed>
					<researchPoints>850</researchPoints>
					<fuelPerTile>6.75</fuelPerTile>
					<customResearchDefNames />
					<bombingCapable>True</bombingCapable>
					<numberBombs>2</numberBombs>
					<radiusDrop>4</radiusDrop>
					<distanceBetweenDrops>3</distanceBetweenDrops>
					<bombingSpeed>0.9</bombingSpeed>
					<precisionBombingNumBombs>2</precisionBombingNumBombs>
				</li>
				<li>
					<defaultValues>True</defaultValues>
					<massCapacity>1590</massCapacity>
					<minPassengers>2</minPassengers>
					<maxPassengers>8</maxPassengers>
					<flightSpeed>6</flightSpeed>
					<researchPoints>850</researchPoints>
					<fuelPerTile>8.75</fuelPerTile>
					<customResearchDefNames />
					<radiusDrop>1</radiusDrop>
					<distanceBetweenDrops>10</distanceBetweenDrops>
					<bombingSpeed>1</bombingSpeed>
					<precisionBombingNumBombs>1</precisionBombingNumBombs>
				</li>
				<li>
					<defaultValues>True</defaultValues>
					<massCapacity>4590</massCapacity>
					<minPassengers>2</minPassengers>
					<maxPassengers>8</maxPassengers>
					<flightSpeed>5.5</flightSpeed>
					<researchPoints>850</researchPoints>
					<fuelPerTile>7.75</fuelPerTile>
					<customResearchDefNames />
					<radiusDrop>1</radiusDrop>
					<distanceBetweenDrops>10</distanceBetweenDrops>
					<bombingSpeed>1</bombingSpeed>
					<precisionBombingNumBombs>1</precisionBombingNumBombs>
				</li>
				<li>
					<defaultValues>True</defaultValues>
					<massCapacity>150</massCapacity>
					<minPassengers>1</minPassengers>
					<maxPassengers>1</maxPassengers>
					<flightSpeed>5</flightSpeed>
					<researchPoints>600</researchPoints>
					<fuelPerTile>4.75</fuelPerTile>
					<customResearchDefNames />
					<bombingCapable>True</bombingCapable>
					<numberBombs>1</numberBombs>
					<radiusDrop>4</radiusDrop>
					<distanceBetweenDrops>3</distanceBetweenDrops>
					<bombingSpeed>0.6</bombingSpeed>
					<precisionBombingNumBombs>1</precisionBombingNumBombs>
				</li>
				<li>
					<defaultValues>True</defaultValues>
					<massCapacity>400</massCapacity>
					<minPassengers>1</minPassengers>
					<maxPassengers>1</maxPassengers>
					<flightSpeed>9</flightSpeed>
					<researchPoints>950</researchPoints>
					<fuelPerTile>6.75</fuelPerTile>
					<customResearchDefNames />
					<bombingCapable>True</bombingCapable>
					<numberBombs>2</numberBombs>
					<radiusDrop>1</radiusDrop>
					<distanceBetweenDrops>3</distanceBetweenDrops>
					<bombingSpeed>1.1</bombingSpeed>
					<precisionBombingNumBombs>2</precisionBombingNumBombs>
				</li>
				<li>
					<defaultValues>True</defaultValues>
					<massCapacity>3000</massCapacity>
					<minPassengers>2</minPassengers>
					<maxPassengers>4</maxPassengers>
					<flightSpeed>6</flightSpeed>
					<researchPoints>950</researchPoints>
					<fuelPerTile>9.75</fuelPerTile>
					<customResearchDefNames />
					<bombingCapable>True</bombingCapable>
					<numberBombs>8</numberBombs>
					<radiusDrop>8</radiusDrop>
					<distanceBetweenDrops>4</distanceBetweenDrops>
					<bombingSpeed>0.8</bombingSpeed>
					<precisionBombingNumBombs>8</precisionBombingNumBombs>
				</li>
				<li>
					<defaultValues>True</defaultValues>
					<massCapacity>500</massCapacity>
					<minPassengers>1</minPassengers>
					<maxPassengers>1</maxPassengers>
					<flightSpeed>8.5</flightSpeed>
					<researchPoints>950</researchPoints>
					<fuelPerTile>6.85</fuelPerTile>
					<customResearchDefNames />
					<bombingCapable>True</bombingCapable>
					<numberBombs>2</numberBombs>
					<radiusDrop>2</radiusDrop>
					<distanceBetweenDrops>3</distanceBetweenDrops>
					<bombingSpeed>1.1</bombingSpeed>
					<precisionBombingNumBombs>2</precisionBombingNumBombs>
				</li>
				<li>
					<defaultValues>True</defaultValues>
					<massCapacity>500</massCapacity>
					<minPassengers>1</minPassengers>
					<maxPassengers>1</maxPassengers>
					<flightSpeed>8.9</flightSpeed>
					<researchPoints>950</researchPoints>
					<fuelPerTile>6.85</fuelPerTile>
					<customResearchDefNames />
					<bombingCapable>True</bombingCapable>
					<numberBombs>2</numberBombs>
					<radiusDrop>2</radiusDrop>
					<distanceBetweenDrops>3</distanceBetweenDrops>
					<bombingSpeed>1.2</bombingSpeed>
					<precisionBombingNumBombs>2</precisionBombingNumBombs>
				</li>
				<li>
					<defaultValues>True</defaultValues>
					<massCapacity>5600</massCapacity>
					<minPassengers>2</minPassengers>
					<maxPassengers>6</maxPassengers>
					<flightSpeed>7</flightSpeed>
					<researchPoints>1000</researchPoints>
					<fuelPerTile>10.75</fuelPerTile>
					<customResearchDefNames />
					<bombingCapable>True</bombingCapable>
					<numberBombs>12</numberBombs>
					<radiusDrop>8</radiusDrop>
					<distanceBetweenDrops>8</distanceBetweenDrops>
					<bombingSpeed>0.8</bombingSpeed>
					<precisionBombingNumBombs>12</precisionBombingNumBombs>
				</li>
				<li>
					<defaultValues>True</defaultValues>
					<massCapacity>800</massCapacity>
					<minPassengers>1</minPassengers>
					<maxPassengers>1</maxPassengers>
					<flightSpeed>10.5</flightSpeed>
					<researchPoints>1200</researchPoints>
					<fuelPerTile>7.85</fuelPerTile>
					<customResearchDefNames />
					<bombingCapable>True</bombingCapable>
					<numberBombs>4</numberBombs>
					<radiusDrop>2</radiusDrop>
					<distanceBetweenDrops>4</distanceBetweenDrops>
					<bombingSpeed>1.3</bombingSpeed>
					<precisionBombingNumBombs>4</precisionBombingNumBombs>
				</li>
				<li>
					<defaultValues>True</defaultValues>
					<massCapacity>350</massCapacity>
					<minPassengers>1</minPassengers>
					<maxPassengers>2</maxPassengers>
					<flightSpeed>6</flightSpeed>
					<researchPoints>850</researchPoints>
					<fuelPerTile>5.75</fuelPerTile>
					<customResearchDefNames />
					<bombingCapable>True</bombingCapable>
					<numberBombs>4</numberBombs>
					<radiusDrop>1</radiusDrop>
					<distanceBetweenDrops>3</distanceBetweenDrops>
					<bombingSpeed>1</bombingSpeed>
					<precisionBombingNumBombs>4</precisionBombingNumBombs>
				</li>
				<li>
					<defaultValues>True</defaultValues>
					<massCapacity>5600</massCapacity>
					<minPassengers>2</minPassengers>
					<maxPassengers>4</maxPassengers>
					<flightSpeed>7</flightSpeed>
					<researchPoints>1000</researchPoints>
					<fuelPerTile>10.75</fuelPerTile>
					<customResearchDefNames />
					<bombingCapable>True</bombingCapable>
					<numberBombs>8</numberBombs>
					<radiusDrop>8</radiusDrop>
					<distanceBetweenDrops>8</distanceBetweenDrops>
					<bombingSpeed>0.8</bombingSpeed>
					<precisionBombingNumBombs>8</precisionBombingNumBombs>
				</li>
				<li>
					<defaultValues>True</defaultValues>
					<massCapacity>1000</massCapacity>
					<minPassengers>2</minPassengers>
					<maxPassengers>2</maxPassengers>
					<flightSpeed>11.2</flightSpeed>
					<researchPoints>1200</researchPoints>
					<fuelPerTile>7.55</fuelPerTile>
					<customResearchDefNames />
					<bombingCapable>True</bombingCapable>
					<numberBombs>6</numberBombs>
					<radiusDrop>2</radiusDrop>
					<distanceBetweenDrops>4</distanceBetweenDrops>
					<bombingSpeed>1.2</bombingSpeed>
					<precisionBombingNumBombs>6</precisionBombingNumBombs>
				</li>
				<li>
					<defaultValues>True</defaultValues>
					<massCapacity>50000</massCapacity>
					<minPassengers>2</minPassengers>
					<maxPassengers>12</maxPassengers>
					<flightSpeed>6</flightSpeed>
					<researchPoints>1780</researchPoints>
					<fuelPerTile>6.75</fuelPerTile>
					<customResearchDefNames />
					<radiusDrop>1</radiusDrop>
					<distanceBetweenDrops>10</distanceBetweenDrops>
					<bombingSpeed>1</bombingSpeed>
					<precisionBombingNumBombs>1</precisionBombingNumBombs>
				</li>
				<li>
					<defaultValues>True</defaultValues>
					<massCapacity>5400</massCapacity>
					<minPassengers>1</minPassengers>
					<maxPassengers>1</maxPassengers>
					<flightSpeed>12.5</flightSpeed>
					<researchPoints>1980</researchPoints>
					<fuelPerTile>15.85</fuelPerTile>
					<customResearchDefNames />
					<bombingCapable>True</bombingCapable>
					<numberBombs>6</numberBombs>
					<radiusDrop>2</radiusDrop>
					<distanceBetweenDrops>4</distanceBetweenDrops>
					<bombingSpeed>1.8</bombingSpeed>
					<precisionBombingNumBombs>6</precisionBombingNumBombs>
				</li>
				<li>
					<defaultValues>True</defaultValues>
					<massCapacity>12000</massCapacity>
					<minPassengers>2</minPassengers>
					<maxPassengers>4</maxPassengers>
					<flightSpeed>13.5</flightSpeed>
					<researchPoints>2400</researchPoints>
					<fuelPerTile>10.85</fuelPerTile>
					<customResearchDefNames />
					<bombingCapable>True</bombingCapable>
					<numberBombs>16</numberBombs>
					<radiusDrop>5</radiusDrop>
					<distanceBetweenDrops>4</distanceBetweenDrops>
					<bombingSpeed>1.5</bombingSpeed>
					<precisionBombingNumBombs>16</precisionBombingNumBombs>
				</li>
				<li>
					<defaultValues>True</defaultValues>
					<massCapacity>4000</massCapacity>
					<minPassengers>1</minPassengers>
					<maxPassengers>1</maxPassengers>
					<flightSpeed>13.5</flightSpeed>
					<researchPoints>1980</researchPoints>
					<fuelPerTile>15.85</fuelPerTile>
					<customResearchDefNames />
					<bombingCapable>True</bombingCapable>
					<numberBombs>6</numberBombs>
					<radiusDrop>2</radiusDrop>
					<distanceBetweenDrops>4</distanceBetweenDrops>
					<bombingSpeed>1.8</bombingSpeed>
					<precisionBombingNumBombs>6</precisionBombingNumBombs>
				</li>
				<li>
					<defaultValues>True</defaultValues>
					<massCapacity>3190</massCapacity>
					<minPassengers>1</minPassengers>
					<maxPassengers>1</maxPassengers>
					<flightSpeed>13.6</flightSpeed>
					<researchPoints>1980</researchPoints>
					<fuelPerTile>15.85</fuelPerTile>
					<customResearchDefNames />
					<bombingCapable>True</bombingCapable>
					<numberBombs>6</numberBombs>
					<radiusDrop>2</radiusDrop>
					<distanceBetweenDrops>4</distanceBetweenDrops>
					<bombingSpeed>1.8</bombingSpeed>
					<precisionBombingNumBombs>6</precisionBombingNumBombs>
				</li>
				<li>
					<defaultValues>True</defaultValues>
					<massCapacity>2100</massCapacity>
					<minPassengers>1</minPassengers>
					<maxPassengers>1</maxPassengers>
					<flightSpeed>14.5</flightSpeed>
					<researchPoints>1980</researchPoints>
					<fuelPerTile>14.85</fuelPerTile>
					<customResearchDefNames />
					<bombingCapable>True</bombingCapable>
					<numberBombs>4</numberBombs>
					<radiusDrop>2</radiusDrop>
					<distanceBetweenDrops>4</distanceBetweenDrops>
					<bombingSpeed>1.8</bombingSpeed>
					<precisionBombingNumBombs>4</precisionBombingNumBombs>
				</li>
				<li>
					<defaultValues>True</defaultValues>
					<massCapacity>8000</massCapacity>
					<minPassengers>2</minPassengers>
					<maxPassengers>5</maxPassengers>
					<flightSpeed>14.5</flightSpeed>
					<researchPoints>2040</researchPoints>
					<fuelPerTile>8.85</fuelPerTile>
					<customResearchDefNames />
					<bombingCapable>True</bombingCapable>
					<numberBombs>24</numberBombs>
					<radiusDrop>4</radiusDrop>
					<distanceBetweenDrops>8</distanceBetweenDrops>
					<bombingSpeed>1.5</bombingSpeed>
					<precisionBombingNumBombs>24</precisionBombingNumBombs>
				</li>
				<li>
					<defaultValues>True</defaultValues>
					<massCapacity>1900</massCapacity>
					<minPassengers>1</minPassengers>
					<maxPassengers>1</maxPassengers>
					<flightSpeed>16.5</flightSpeed>
					<researchPoints>1980</researchPoints>
					<fuelPerTile>14.85</fuelPerTile>
					<customResearchDefNames />
					<bombingCapable>True</bombingCapable>
					<numberBombs>4</numberBombs>
					<radiusDrop>2</radiusDrop>
					<distanceBetweenDrops>4</distanceBetweenDrops>
					<bombingSpeed>2</bombingSpeed>
					<precisionBombingNumBombs>4</precisionBombingNumBombs>
				</li>
				<li>
					<defaultValues>True</defaultValues>
					<massCapacity>2800</massCapacity>
					<minPassengers>1</minPassengers>
					<maxPassengers>1</maxPassengers>
					<flightSpeed>18.5</flightSpeed>
					<researchPoints>2200</researchPoints>
					<fuelPerTile>13.85</fuelPerTile>
					<customResearchDefNames />
					<bombingCapable>True</bombingCapable>
					<numberBombs>6</numberBombs>
					<radiusDrop>2</radiusDrop>
					<distanceBetweenDrops>4</distanceBetweenDrops>
					<bombingSpeed>2</bombingSpeed>
					<precisionBombingNumBombs>6</precisionBombingNumBombs>
				</li>
				<li>
					<defaultValues>True</defaultValues>
					<massCapacity>3800</massCapacity>
					<minPassengers>1</minPassengers>
					<maxPassengers>1</maxPassengers>
					<flightSpeed>19.5</flightSpeed>
					<researchPoints>2200</researchPoints>
					<fuelPerTile>15.85</fuelPerTile>
					<customResearchDefNames />
					<bombingCapable>True</bombingCapable>
					<numberBombs>4</numberBombs>
					<radiusDrop>2</radiusDrop>
					<distanceBetweenDrops>4</distanceBetweenDrops>
					<bombingSpeed>2.5</bombingSpeed>
					<precisionBombingNumBombs>4</precisionBombingNumBombs>
				</li>
				<li>
					<defaultValues>True</defaultValues>
					<massCapacity>3400</massCapacity>
					<minPassengers>1</minPassengers>
					<maxPassengers>1</maxPassengers>
					<flightSpeed>19.8</flightSpeed>
					<researchPoints>2200</researchPoints>
					<fuelPerTile>15.25</fuelPerTile>
					<customResearchDefNames />
					<bombingCapable>True</bombingCapable>
					<numberBombs>4</numberBombs>
					<radiusDrop>2</radiusDrop>
					<distanceBetweenDrops>4</distanceBetweenDrops>
					<bombingSpeed>2.5</bombingSpeed>
					<precisionBombingNumBombs>4</precisionBombingNumBombs>
				</li>
				<li>
					<defaultValues>True</defaultValues>
					<massCapacity>3800</massCapacity>
					<minPassengers>2</minPassengers>
					<maxPassengers>4</maxPassengers>
					<flightSpeed>8</flightSpeed>
					<researchPoints>950</researchPoints>
					<fuelPerTile>7.75</fuelPerTile>
					<customResearchDefNames />
					<bombingCapable>True</bombingCapable>
					<numberBombs>8</numberBombs>
					<radiusDrop>4</radiusDrop>
					<distanceBetweenDrops>4</distanceBetweenDrops>
					<bombingSpeed>0.8</bombingSpeed>
					<precisionBombingNumBombs>8</precisionBombingNumBombs>
				</li>
				<li>
					<defaultValues>True</defaultValues>
					<massCapacity>12000</massCapacity>
					<minPassengers>2</minPassengers>
					<maxPassengers>4</maxPassengers>
					<flightSpeed>13.5</flightSpeed>
					<researchPoints>2400</researchPoints>
					<fuelPerTile>8.85</fuelPerTile>
					<customResearchDefNames />
					<bombingCapable>True</bombingCapable>
					<numberBombs>24</numberBombs>
					<radiusDrop>6</radiusDrop>
					<distanceBetweenDrops>4</distanceBetweenDrops>
					<bombingSpeed>1.3</bombingSpeed>
					<precisionBombingNumBombs>24</precisionBombingNumBombs>
				</li>
				<li>
					<defaultValues>True</defaultValues>
					<massCapacity>20000</massCapacity>
					<minPassengers>2</minPassengers>
					<maxPassengers>12</maxPassengers>
					<flightSpeed>7</flightSpeed>
					<researchPoints>1780</researchPoints>
					<fuelPerTile>6.75</fuelPerTile>
					<customResearchDefNames />
					<radiusDrop>1</radiusDrop>
					<distanceBetweenDrops>10</distanceBetweenDrops>
					<bombingSpeed>1</bombingSpeed>
					<precisionBombingNumBombs>1</precisionBombingNumBombs>
				</li>
				<li>
					<defaultValues>True</defaultValues>
					<massCapacity>3500</massCapacity>
					<minPassengers>2</minPassengers>
					<maxPassengers>4</maxPassengers>
					<flightSpeed>7</flightSpeed>
					<researchPoints>850</researchPoints>
					<fuelPerTile>7.75</fuelPerTile>
					<customResearchDefNames />
					<bombingCapable>True</bombingCapable>
					<numberBombs>6</numberBombs>
					<radiusDrop>4</radiusDrop>
					<distanceBetweenDrops>4</distanceBetweenDrops>
					<bombingSpeed>0.7</bombingSpeed>
					<precisionBombingNumBombs>6</precisionBombingNumBombs>
				</li>
				<li>
					<defaultValues>True</defaultValues>
					<massCapacity>15000</massCapacity>
					<minPassengers>2</minPassengers>
					<maxPassengers>6</maxPassengers>
					<flightSpeed>11.5</flightSpeed>
					<researchPoints>2400</researchPoints>
					<fuelPerTile>8.95</fuelPerTile>
					<customResearchDefNames />
					<bombingCapable>True</bombingCapable>
					<numberBombs>18</numberBombs>
					<radiusDrop>4</radiusDrop>
					<distanceBetweenDrops>2</distanceBetweenDrops>
					<bombingSpeed>1.3</bombingSpeed>
					<precisionBombingNumBombs>18</precisionBombingNumBombs>
				</li>
				<li>
					<defaultValues>True</defaultValues>
					<massCapacity>6700</massCapacity>
					<minPassengers>1</minPassengers>
					<maxPassengers>1</maxPassengers>
					<flightSpeed>20</flightSpeed>
					<researchPoints>2080</researchPoints>
					<fuelPerTile>18.85</fuelPerTile>
					<customResearchDefNames />
					<bombingCapable>True</bombingCapable>
					<numberBombs>6</numberBombs>
					<radiusDrop>2</radiusDrop>
					<distanceBetweenDrops>4</distanceBetweenDrops>
					<bombingSpeed>2.5</bombingSpeed>
					<precisionBombingNumBombs>6</precisionBombingNumBombs>
				</li>
				<li>
					<defaultValues>True</defaultValues>
					<massCapacity>6600</massCapacity>
					<minPassengers>1</minPassengers>
					<maxPassengers>1</maxPassengers>
					<flightSpeed>20</flightSpeed>
					<researchPoints>2080</researchPoints>
					<fuelPerTile>18.75</fuelPerTile>
					<customResearchDefNames />
					<bombingCapable>True</bombingCapable>
					<numberBombs>6</numberBombs>
					<radiusDrop>2</radiusDrop>
					<distanceBetweenDrops>4</distanceBetweenDrops>
					<bombingSpeed>2.5</bombingSpeed>
					<precisionBombingNumBombs>6</precisionBombingNumBombs>
				</li>
				<li>
					<defaultValues>True</defaultValues>
					<massCapacity>4200</massCapacity>
					<minPassengers>1</minPassengers>
					<maxPassengers>1</maxPassengers>
					<flightSpeed>20</flightSpeed>
					<researchPoints>2080</researchPoints>
					<fuelPerTile>15.85</fuelPerTile>
					<customResearchDefNames />
					<bombingCapable>True</bombingCapable>
					<numberBombs>6</numberBombs>
					<radiusDrop>2</radiusDrop>
					<distanceBetweenDrops>4</distanceBetweenDrops>
					<bombingSpeed>2.5</bombingSpeed>
					<precisionBombingNumBombs>6</precisionBombingNumBombs>
				</li>
				<li>
					<defaultValues>True</defaultValues>
					<massCapacity>9000</massCapacity>
					<minPassengers>1</minPassengers>
					<maxPassengers>1</maxPassengers>
					<flightSpeed>20</flightSpeed>
					<researchPoints>2080</researchPoints>
					<fuelPerTile>15.85</fuelPerTile>
					<customResearchDefNames />
					<bombingCapable>True</bombingCapable>
					<numberBombs>6</numberBombs>
					<radiusDrop>2</radiusDrop>
					<distanceBetweenDrops>4</distanceBetweenDrops>
					<bombingSpeed>2.5</bombingSpeed>
					<precisionBombingNumBombs>6</precisionBombingNumBombs>
				</li>
				<li>
					<defaultValues>True</defaultValues>
					<massCapacity>7200</massCapacity>
					<minPassengers>1</minPassengers>
					<maxPassengers>1</maxPassengers>
					<flightSpeed>15</flightSpeed>
					<researchPoints>1890</researchPoints>
					<fuelPerTile>11.85</fuelPerTile>
					<customResearchDefNames />
					<bombingCapable>True</bombingCapable>
					<numberBombs>8</numberBombs>
					<radiusDrop>2</radiusDrop>
					<distanceBetweenDrops>4</distanceBetweenDrops>
					<bombingSpeed>1.9</bombingSpeed>
					<precisionBombingNumBombs>8</precisionBombingNumBombs>
				</li>
				<li>
					<defaultValues>True</defaultValues>
					<massCapacity>12000</massCapacity>
					<minPassengers>2</minPassengers>
					<maxPassengers>6</maxPassengers>
					<flightSpeed>7</flightSpeed>
					<researchPoints>1200</researchPoints>
					<fuelPerTile>11.75</fuelPerTile>
					<customResearchDefNames />
					<bombingCapable>True</bombingCapable>
					<numberBombs>12</numberBombs>
					<radiusDrop>8</radiusDrop>
					<distanceBetweenDrops>8</distanceBetweenDrops>
					<bombingSpeed>0.8</bombingSpeed>
					<precisionBombingNumBombs>12</precisionBombingNumBombs>
				</li>
				<li>
					<defaultValues>True</defaultValues>
					<massCapacity>6514</massCapacity>
					<minPassengers>1</minPassengers>
					<maxPassengers>1</maxPassengers>
					<flightSpeed>22</flightSpeed>
					<researchPoints>1890</researchPoints>
					<fuelPerTile>17.85</fuelPerTile>
					<customResearchDefNames />
					<bombingCapable>True</bombingCapable>
					<numberBombs>9</numberBombs>
					<radiusDrop>2</radiusDrop>
					<distanceBetweenDrops>4</distanceBetweenDrops>
					<bombingSpeed>2.5</bombingSpeed>
					<precisionBombingNumBombs>9</precisionBombingNumBombs>
				</li>
				<li>
					<defaultValues>True</defaultValues>
					<massCapacity>6100</massCapacity>
					<minPassengers>1</minPassengers>
					<maxPassengers>1</maxPassengers>
					<flightSpeed>20</flightSpeed>
					<researchPoints>2040</researchPoints>
					<fuelPerTile>12.85</fuelPerTile>
					<customResearchDefNames />
					<bombingCapable>True</bombingCapable>
					<numberBombs>6</numberBombs>
					<radiusDrop>2</radiusDrop>
					<distanceBetweenDrops>4</distanceBetweenDrops>
					<bombingSpeed>2.2</bombingSpeed>
					<precisionBombingNumBombs>6</precisionBombingNumBombs>
				</li>
				<li>
					<defaultValues>True</defaultValues>
					<massCapacity>250000</massCapacity>
					<minPassengers>6</minPassengers>
					<maxPassengers>32</maxPassengers>
					<flightSpeed>15</flightSpeed>
					<researchPoints>2440</researchPoints>
					<fuelPerTile>25.75</fuelPerTile>
					<customResearchDefNames />
					<radiusDrop>1</radiusDrop>
					<distanceBetweenDrops>10</distanceBetweenDrops>
					<bombingSpeed>1</bombingSpeed>
					<precisionBombingNumBombs>1</precisionBombingNumBombs>
				</li>
				<li>
					<defaultValues>True</defaultValues>
					<massCapacity>12500</massCapacity>
					<minPassengers>1</minPassengers>
					<maxPassengers>1</maxPassengers>
					<flightSpeed>23</flightSpeed>
					<researchPoints>2440</researchPoints>
					<fuelPerTile>20.75</fuelPerTile>
					<customResearchDefNames />
					<bombingCapable>True</bombingCapable>
					<numberBombs>16</numberBombs>
					<radiusDrop>2</radiusDrop>
					<distanceBetweenDrops>4</distanceBetweenDrops>
					<bombingSpeed>2.5</bombingSpeed>
					<precisionBombingNumBombs>16</precisionBombingNumBombs>
				</li>
				<li>
					<defaultValues>True</defaultValues>
					<massCapacity>13100</massCapacity>
					<minPassengers>1</minPassengers>
					<maxPassengers>1</maxPassengers>
					<flightSpeed>22</flightSpeed>
					<researchPoints>2040</researchPoints>
					<fuelPerTile>18.85</fuelPerTile>
					<customResearchDefNames />
					<bombingCapable>True</bombingCapable>
					<numberBombs>5</numberBombs>
					<radiusDrop>2</radiusDrop>
					<distanceBetweenDrops>4</distanceBetweenDrops>
					<bombingSpeed>2.2</bombingSpeed>
					<precisionBombingNumBombs>5</precisionBombingNumBombs>
				</li>
				<li>
					<defaultValues>True</defaultValues>
					<massCapacity>17100</massCapacity>
					<minPassengers>1</minPassengers>
					<maxPassengers>1</maxPassengers>
					<flightSpeed>23</flightSpeed>
					<researchPoints>2440</researchPoints>
					<fuelPerTile>19.85</fuelPerTile>
					<customResearchDefNames />
					<bombingCapable>True</bombingCapable>
					<numberBombs>8</numberBombs>
					<radiusDrop>2</radiusDrop>
					<distanceBetweenDrops>4</distanceBetweenDrops>
					<bombingSpeed>2.2</bombingSpeed>
					<precisionBombingNumBombs>8</precisionBombingNumBombs>
				</li>
				<li>
					<defaultValues>True</defaultValues>
					<massCapacity>20500</massCapacity>
					<minPassengers>1</minPassengers>
					<maxPassengers>1</maxPassengers>
					<flightSpeed>22</flightSpeed>
					<researchPoints>2440</researchPoints>
					<fuelPerTile>19.95</fuelPerTile>
					<customResearchDefNames />
					<bombingCapable>True</bombingCapable>
					<numberBombs>8</numberBombs>
					<radiusDrop>2</radiusDrop>
					<distanceBetweenDrops>4</distanceBetweenDrops>
					<bombingSpeed>2.2</bombingSpeed>
					<precisionBombingNumBombs>8</precisionBombingNumBombs>
				</li>
				<li>
					<defaultValues>True</defaultValues>
					<massCapacity>18350</massCapacity>
					<minPassengers>2</minPassengers>
					<maxPassengers>2</maxPassengers>
					<flightSpeed>20</flightSpeed>
					<researchPoints>2640</researchPoints>
					<fuelPerTile>8.85</fuelPerTile>
					<customResearchDefNames />
					<bombingCapable>True</bombingCapable>
					<numberBombs>80</numberBombs>
					<radiusDrop>12</radiusDrop>
					<distanceBetweenDrops>2</distanceBetweenDrops>
					<bombingSpeed>1.5</bombingSpeed>
					<precisionBombingNumBombs>80</precisionBombingNumBombs>
				</li>
				<li>
					<defaultValues>True</defaultValues>
					<massCapacity>22500</massCapacity>
					<minPassengers>1</minPassengers>
					<maxPassengers>1</maxPassengers>
					<flightSpeed>25</flightSpeed>
					<researchPoints>2440</researchPoints>
					<fuelPerTile>22.95</fuelPerTile>
					<customResearchDefNames />
					<bombingCapable>True</bombingCapable>
					<numberBombs>8</numberBombs>
					<radiusDrop>2</radiusDrop>
					<distanceBetweenDrops>4</distanceBetweenDrops>
					<bombingSpeed>2.2</bombingSpeed>
					<precisionBombingNumBombs>8</precisionBombingNumBombs>
				</li>
				<li>
					<defaultValues>True</defaultValues>
					<massCapacity>9390</massCapacity>
					<minPassengers>2</minPassengers>
					<maxPassengers>25</maxPassengers>
					<flightSpeed>12</flightSpeed>
					<researchPoints>2040</researchPoints>
					<fuelPerTile>12.75</fuelPerTile>
					<customResearchDefNames />
					<radiusDrop>1</radiusDrop>
					<distanceBetweenDrops>10</distanceBetweenDrops>
					<bombingSpeed>1</bombingSpeed>
					<precisionBombingNumBombs>1</precisionBombingNumBombs>
				</li>
				<li>
					<defaultValues>True</defaultValues>
					<massCapacity>10000</massCapacity>
					<minPassengers>2</minPassengers>
					<maxPassengers>2</maxPassengers>
					<flightSpeed>20</flightSpeed>
					<researchPoints>2080</researchPoints>
					<fuelPerTile>19.95</fuelPerTile>
					<customResearchDefNames />
					<bombingCapable>True</bombingCapable>
					<numberBombs>8</numberBombs>
					<radiusDrop>2</radiusDrop>
					<distanceBetweenDrops>4</distanceBetweenDrops>
					<bombingSpeed>2.2</bombingSpeed>
					<precisionBombingNumBombs>8</precisionBombingNumBombs>
				</li>
				<li>
					<defaultValues>True</defaultValues>
					<massCapacity>8600</massCapacity>
					<minPassengers>2</minPassengers>
					<maxPassengers>2</maxPassengers>
					<flightSpeed>17.5</flightSpeed>
					<researchPoints>1980</researchPoints>
					<fuelPerTile>16.85</fuelPerTile>
					<customResearchDefNames />
					<bombingCapable>True</bombingCapable>
					<numberBombs>8</numberBombs>
					<radiusDrop>4</radiusDrop>
					<distanceBetweenDrops>4</distanceBetweenDrops>
					<bombingSpeed>1.8</bombingSpeed>
					<precisionBombingNumBombs>8</precisionBombingNumBombs>
				</li>
				<li>
					<defaultValues>True</defaultValues>
					<massCapacity>77619</massCapacity>
					<minPassengers>3</minPassengers>
					<maxPassengers>106</maxPassengers>
					<flightSpeed>14.5</flightSpeed>
					<researchPoints>2440</researchPoints>
					<fuelPerTile>25.75</fuelPerTile>
					<customResearchDefNames />
					<radiusDrop>1</radiusDrop>
					<distanceBetweenDrops>10</distanceBetweenDrops>
					<bombingSpeed>1</bombingSpeed>
					<precisionBombingNumBombs>1</precisionBombingNumBombs>
				</li>
				<li>
					<defaultValues>True</defaultValues>
					<massCapacity>127459</massCapacity>
					<minPassengers>4</minPassengers>
					<maxPassengers>7</maxPassengers>
					<flightSpeed>14.5</flightSpeed>
					<researchPoints>2440</researchPoints>
					<fuelPerTile>26.75</fuelPerTile>
					<customResearchDefNames />
					<radiusDrop>1</radiusDrop>
					<distanceBetweenDrops>10</distanceBetweenDrops>
					<bombingSpeed>1</bombingSpeed>
					<precisionBombingNumBombs>1</precisionBombingNumBombs>
				</li>
				<li>
					<defaultValues>True</defaultValues>
					<massCapacity>24000</massCapacity>
					<minPassengers>4</minPassengers>
					<maxPassengers>4</maxPassengers>
					<flightSpeed>15.4</flightSpeed>
					<researchPoints>2200</researchPoints>
					<fuelPerTile>9.85</fuelPerTile>
					<customResearchDefNames />
					<bombingCapable>True</bombingCapable>
					<numberBombs>32</numberBombs>
					<radiusDrop>6</radiusDrop>
					<distanceBetweenDrops>4</distanceBetweenDrops>
					<bombingSpeed>1.5</bombingSpeed>
					<precisionBombingNumBombs>32</precisionBombingNumBombs>
				</li>
				<li>
					<defaultValues>True</defaultValues>
					<massCapacity>12000</massCapacity>
					<minPassengers>1</minPassengers>
					<maxPassengers>1</maxPassengers>
					<flightSpeed>21</flightSpeed>
					<researchPoints>2640</researchPoints>
					<fuelPerTile>19.95</fuelPerTile>
					<customResearchDefNames />
					<bombingCapable>True</bombingCapable>
					<numberBombs>2</numberBombs>
					<radiusDrop>2</radiusDrop>
					<distanceBetweenDrops>2</distanceBetweenDrops>
					<bombingSpeed>1.8</bombingSpeed>
					<precisionBombingNumBombs>2</precisionBombingNumBombs>
				</li>
				<li>
					<defaultValues>True</defaultValues>
					<massCapacity>8000</massCapacity>
					<minPassengers>2</minPassengers>
					<maxPassengers>2</maxPassengers>
					<flightSpeed>8</flightSpeed>
					<researchPoints>1000</researchPoints>
					<fuelPerTile>9.85</fuelPerTile>
					<customResearchDefNames />
					<bombingCapable>True</bombingCapable>
					<numberBombs>16</numberBombs>
					<radiusDrop>6</radiusDrop>
					<distanceBetweenDrops>8</distanceBetweenDrops>
					<bombingSpeed>1</bombingSpeed>
					<precisionBombingNumBombs>16</precisionBombingNumBombs>
				</li>
				<li>
					<defaultValues>True</defaultValues>
					<massCapacity>8500</massCapacity>
					<minPassengers>1</minPassengers>
					<maxPassengers>1</maxPassengers>
					<flightSpeed>21</flightSpeed>
					<researchPoints>2840</researchPoints>
					<fuelPerTile>20.95</fuelPerTile>
					<customResearchDefNames />
					<bombingCapable>True</bombingCapable>
					<numberBombs>11</numberBombs>
					<radiusDrop>2</radiusDrop>
					<distanceBetweenDrops>4</distanceBetweenDrops>
					<bombingSpeed>2.2</bombingSpeed>
					<precisionBombingNumBombs>11</precisionBombingNumBombs>
				</li>
				<li>
					<defaultValues>True</defaultValues>
					<massCapacity>9500</massCapacity>
					<minPassengers>1</minPassengers>
					<maxPassengers>1</maxPassengers>
					<flightSpeed>22</flightSpeed>
					<researchPoints>2840</researchPoints>
					<fuelPerTile>21.35</fuelPerTile>
					<customResearchDefNames />
					<bombingCapable>True</bombingCapable>
					<numberBombs>14</numberBombs>
					<radiusDrop>2</radiusDrop>
					<distanceBetweenDrops>4</distanceBetweenDrops>
					<bombingSpeed>2.2</bombingSpeed>
					<precisionBombingNumBombs>14</precisionBombingNumBombs>
				</li>
				<li>
					<defaultValues>True</defaultValues>
					<massCapacity>150</massCapacity>
					<minPassengers>1</minPassengers>
					<maxPassengers>2</maxPassengers>
					<flightSpeed>3</flightSpeed>
					<researchPoints>500</researchPoints>
					<fuelPerTile>4.75</fuelPerTile>
					<customResearchDefNames />
					<radiusDrop>1</radiusDrop>
					<distanceBetweenDrops>10</distanceBetweenDrops>
					<bombingSpeed>1</bombingSpeed>
					<precisionBombingNumBombs>1</precisionBombingNumBombs>
				</li>
				<li>
					<defaultValues>True</defaultValues>
					<massCapacity>1050</massCapacity>
					<minPassengers>1</minPassengers>
					<maxPassengers>8</maxPassengers>
					<flightSpeed>3.5</flightSpeed>
					<researchPoints>620</researchPoints>
					<fuelPerTile>5.75</fuelPerTile>
					<customResearchDefNames />
					<radiusDrop>1</radiusDrop>
					<distanceBetweenDrops>10</distanceBetweenDrops>
					<bombingSpeed>1</bombingSpeed>
					<precisionBombingNumBombs>1</precisionBombingNumBombs>
				</li>
				<li>
					<defaultValues>True</defaultValues>
					<massCapacity>1550</massCapacity>
					<minPassengers>2</minPassengers>
					<maxPassengers>6</maxPassengers>
					<flightSpeed>3.6</flightSpeed>
					<researchPoints>950</researchPoints>
					<fuelPerTile>6.75</fuelPerTile>
					<customResearchDefNames />
					<radiusDrop>1</radiusDrop>
					<distanceBetweenDrops>10</distanceBetweenDrops>
					<bombingSpeed>1</bombingSpeed>
					<precisionBombingNumBombs>1</precisionBombingNumBombs>
				</li>
				<li>
					<defaultValues>True</defaultValues>
					<massCapacity>250</massCapacity>
					<minPassengers>2</minPassengers>
					<maxPassengers>2</maxPassengers>
					<flightSpeed>3.8</flightSpeed>
					<researchPoints>620</researchPoints>
					<fuelPerTile>5.75</fuelPerTile>
					<customResearchDefNames />
					<radiusDrop>1</radiusDrop>
					<distanceBetweenDrops>10</distanceBetweenDrops>
					<bombingSpeed>1</bombingSpeed>
					<precisionBombingNumBombs>1</precisionBombingNumBombs>
				</li>
				<li>
					<defaultValues>True</defaultValues>
					<massCapacity>1690</massCapacity>
					<minPassengers>2</minPassengers>
					<maxPassengers>11</maxPassengers>
					<flightSpeed>3.6</flightSpeed>
					<researchPoints>950</researchPoints>
					<fuelPerTile>6.75</fuelPerTile>
					<customResearchDefNames />
					<bombingCapable>True</bombingCapable>
					<numberBombs>2</numberBombs>
					<radiusDrop>2</radiusDrop>
					<distanceBetweenDrops>4</distanceBetweenDrops>
					<bombingSpeed>1</bombingSpeed>
					<precisionBombingNumBombs>2</precisionBombingNumBombs>
				</li>
				<li>
					<defaultValues>True</defaultValues>
					<massCapacity>1760</massCapacity>
					<minPassengers>2</minPassengers>
					<maxPassengers>13</maxPassengers>
					<flightSpeed>3.7</flightSpeed>
					<researchPoints>950</researchPoints>
					<fuelPerTile>6.95</fuelPerTile>
					<customResearchDefNames />
					<radiusDrop>1</radiusDrop>
					<distanceBetweenDrops>10</distanceBetweenDrops>
					<bombingSpeed>1</bombingSpeed>
					<precisionBombingNumBombs>1</precisionBombingNumBombs>
				</li>
				<li>
					<defaultValues>True</defaultValues>
					<massCapacity>40000</massCapacity>
					<minPassengers>2</minPassengers>
					<maxPassengers>196</maxPassengers>
					<flightSpeed>3.6</flightSpeed>
					<researchPoints>1250</researchPoints>
					<fuelPerTile>6.95</fuelPerTile>
					<customResearchDefNames />
					<radiusDrop>1</radiusDrop>
					<distanceBetweenDrops>10</distanceBetweenDrops>
					<bombingSpeed>1</bombingSpeed>
					<precisionBombingNumBombs>1</precisionBombingNumBombs>
				</li>
				<li>
					<defaultValues>True</defaultValues>
					<massCapacity>1900</massCapacity>
					<minPassengers>3</minPassengers>
					<maxPassengers>28</maxPassengers>
					<flightSpeed>3.5</flightSpeed>
					<researchPoints>1250</researchPoints>
					<fuelPerTile>6.75</fuelPerTile>
					<customResearchDefNames />
					<bombingCapable>True</bombingCapable>
					<numberBombs>4</numberBombs>
					<radiusDrop>2</radiusDrop>
					<distanceBetweenDrops>4</distanceBetweenDrops>
					<bombingSpeed>1</bombingSpeed>
					<precisionBombingNumBombs>4</precisionBombingNumBombs>
				</li>
				<li>
					<defaultValues>True</defaultValues>
					<massCapacity>1900</massCapacity>
					<minPassengers>3</minPassengers>
					<maxPassengers>38</maxPassengers>
					<flightSpeed>3.4</flightSpeed>
					<researchPoints>1250</researchPoints>
					<fuelPerTile>6.75</fuelPerTile>
					<customResearchDefNames />
					<radiusDrop>1</radiusDrop>
					<distanceBetweenDrops>10</distanceBetweenDrops>
					<bombingSpeed>1</bombingSpeed>
					<precisionBombingNumBombs>1</precisionBombingNumBombs>
				</li>
				<li>
					<defaultValues>True</defaultValues>
					<massCapacity>2500</massCapacity>
					<minPassengers>2</minPassengers>
					<maxPassengers>2</maxPassengers>
					<flightSpeed>4.1</flightSpeed>
					<researchPoints>1450</researchPoints>
					<fuelPerTile>6.35</fuelPerTile>
					<customResearchDefNames />
					<bombingCapable>True</bombingCapable>
					<numberBombs>6</numberBombs>
					<radiusDrop>2</radiusDrop>
					<distanceBetweenDrops>4</distanceBetweenDrops>
					<bombingSpeed>1</bombingSpeed>
					<precisionBombingNumBombs>6</precisionBombingNumBombs>
				</li>
				<li>
					<defaultValues>True</defaultValues>
					<massCapacity>2900</massCapacity>
					<minPassengers>2</minPassengers>
					<maxPassengers>10</maxPassengers>
					<flightSpeed>3.8</flightSpeed>
					<researchPoints>1450</researchPoints>
					<fuelPerTile>6.4</fuelPerTile>
					<customResearchDefNames />
					<bombingCapable>True</bombingCapable>
					<numberBombs>6</numberBombs>
					<radiusDrop>2</radiusDrop>
					<distanceBetweenDrops>4</distanceBetweenDrops>
					<bombingSpeed>1</bombingSpeed>
					<precisionBombingNumBombs>6</precisionBombingNumBombs>
				</li>
				<li>
					<defaultValues>True</defaultValues>
					<massCapacity>2800</massCapacity>
					<minPassengers>2</minPassengers>
					<maxPassengers>2</maxPassengers>
					<flightSpeed>4.3</flightSpeed>
					<researchPoints>1450</researchPoints>
					<fuelPerTile>6.35</fuelPerTile>
					<customResearchDefNames />
					<bombingCapable>True</bombingCapable>
					<numberBombs>8</numberBombs>
					<radiusDrop>2</radiusDrop>
					<distanceBetweenDrops>4</distanceBetweenDrops>
					<bombingSpeed>1.2</bombingSpeed>
					<precisionBombingNumBombs>8</precisionBombingNumBombs>
				</li>
			</values>
		</defProperties>
		<allowedBombs>
			<li>Shell_HighExplosive</li>
			<li>Shell_Incendiary</li>
			<li>Shell_EMP</li>
			<li>Shell_Smoke</li>
			<li>Shell_Firefoam</li>
			<li>Shell_AntigrainWarhead</li>
			<li>VFEI_Shell_PsychicWarhead</li>
			<li>Shell_Napalm</li>
			<li>Shell_40lb</li>
			<li>Shell_120lb</li>
			<li>Shell_220lb</li>
			<li>Shell_350lb</li>
			<li>Shell_500lb</li>
			<li>Shell_1000lb</li>
			<li>Shell_2100lb</li>
			<li>Shell_3080lb</li>
			<li>Shell_4000lb</li>
			<li>Shell_8000lb</li>
			<li>Shell_12000lb</li>
			<li>Shell_22000lb</li>
			<li>Shell_fatmanNukePyB</li>
			<li>Shell_B28NukePyB</li>
			<li>Shell_500lbNapalm</li>
			<li>Shell_500lbSmoke</li>
			<li>Shell_500lbExtinguish</li>
			<li>Shell_500lbEMP</li>
		</allowedBombs>
		<disallowedBombs />
	</ModSettings>
</SettingsBlock>